[
  {
    "answerOptions": [
      "8718",
      "9552",
      "9165",
      "9606"
    ],
    "correctAnswer": "9606",
    "variables": {
      "a": 4,
      "b": 1359,
      "c": 5,
      "d": 834
    }
  },
  {
    "answerOptions": [
      "5409",
      "5445",
      "5434",
      "5552"
    ],
    "correctAnswer": "5434",
    "variables": {
      "a": 3,
      "b": 874,
      "c": 2,
      "d": 1406
    }
  },
  {
    "answerOptions": [
      "12703",
      "13091",
      "12810",
      "11805"
    ],
    "correctAnswer": "12810",
    "variables": {
      "a": 5,
      "b": 1376,
      "c": 5,
      "d": 1186
    }
  },
  {
    "answerOptions": [
      "9922",
      "10287",
      "9760",
      "10159"
    ],
    "correctAnswer": "9760",
    "variables": {
      "a": 5,
      "b": 1378,
      "c": 2,
      "d": 1435
    }
  },
  {
    "answerOptions": [
      "8667",
      "7746",
      "8317",
      "8200"
    ],
    "correctAnswer": "8200",
    "variables": {
      "a": 4,
      "b": 809,
      "c": 4,
      "d": 1241
    }
  },
  {
    "answerOptions": [
      "9481",
      "9137",
      "9283",
      "9128"
    ],
    "correctAnswer": "9128",
    "variables": {
      "a": 5,
      "b": 828,
      "c": 4,
      "d": 1247
    }
  },
  {
    "answerOptions": [
      "5586",
      "5117",
      "5368",
      "5482"
    ],
    "correctAnswer": "5586",
    "variables": {
      "a": 4,
      "b": 878,
      "c": 2,
      "d": 1037
    }
  },
  {
    "answerOptions": [
      "6381",
      "5828",
      "5421",
      "5850"
    ],
    "correctAnswer": "5850",
    "variables": {
      "a": 1,
      "b": 1170,
      "c": 4,
      "d": 1170
    }
  },
  {
    "answerOptions": [
      "3873",
      "3650",
      "4268",
      "3942"
    ],
    "correctAnswer": "3942",
    "variables": {
      "a": 2,
      "b": 1451,
      "c": 1,
      "d": 1040
    }
  },
  {
    "answerOptions": [
      "3910",
      "3849",
      "4035",
      "3947"
    ],
    "correctAnswer": "3947",
    "variables": {
      "a": 1,
      "b": 1203,
      "c": 2,
      "d": 1372
    }
  },
  {
    "answerOptions": [
      "7291",
      "6751",
      "7128",
      "6218"
    ],
    "correctAnswer": "6751",
    "variables": {
      "a": 5,
      "b": 811,
      "c": 2,
      "d": 1348
    }
  },
  {
    "answerOptions": [
      "5694",
      "5490",
      "6136",
      "5722"
    ],
    "correctAnswer": "5694",
    "variables": {
      "a": 2,
      "b": 1065,
      "c": 4,
      "d": 891
    }
  },
  {
    "answerOptions": [
      "9827",
      "10202",
      "9325",
      "9299"
    ],
    "correctAnswer": "9325",
    "variables": {
      "a": 5,
      "b": 825,
      "c": 5,
      "d": 1040
    }
  },
  {
    "answerOptions": [
      "4874",
      "4949",
      "5214",
      "5060"
    ],
    "correctAnswer": "4949",
    "variables": {
      "a": 1,
      "b": 857,
      "c": 4,
      "d": 1023
    }
  },
  {
    "answerOptions": [
      "6762",
      "6795",
      "6129",
      "6650"
    ],
    "correctAnswer": "6795",
    "variables": {
      "a": 3,
      "b": 1282,
      "c": 3,
      "d": 983
    }
  },
  {
    "answerOptions": [
      "6460",
      "6597",
      "6834",
      "6418"
    ],
    "correctAnswer": "6834",
    "variables": {
      "a": 1,
      "b": 882,
      "c": 4,
      "d": 1488
    }
  },
  {
    "answerOptions": [
      "6204",
      "6180",
      "6686",
      "6653"
    ],
    "correctAnswer": "6686",
    "variables": {
      "a": 1,
      "b": 1386,
      "c": 5,
      "d": 1060
    }
  },
  {
    "answerOptions": [
      "8310",
      "8387",
      "7526",
      "8135"
    ],
    "correctAnswer": "8310",
    "variables": {
      "a": 2,
      "b": 1345,
      "c": 5,
      "d": 1124
    }
  },
  {
    "answerOptions": [
      "4013",
      "3728",
      "3862",
      "4009"
    ],
    "correctAnswer": "3728",
    "variables": {
      "a": 2,
      "b": 1430,
      "c": 1,
      "d": 868
    }
  },
  {
    "answerOptions": [
      "9610",
      "10132",
      "9825",
      "10402"
    ],
    "correctAnswer": "9825",
    "variables": {
      "a": 5,
      "b": 1275,
      "c": 3,
      "d": 1150
    }
  },
  {
    "answerOptions": [
      "6543",
      "7038",
      "6646",
      "7190"
    ],
    "correctAnswer": "6646",
    "variables": {
      "a": 4,
      "b": 1389,
      "c": 1,
      "d": 1090
    }
  },
  {
    "answerOptions": [
      "6591",
      "6703",
      "6770",
      "6163"
    ],
    "correctAnswer": "6163",
    "variables": {
      "a": 2,
      "b": 848,
      "c": 3,
      "d": 1489
    }
  },
  {
    "answerOptions": [
      "7030",
      "6632",
      "5986",
      "6539"
    ],
    "correctAnswer": "6632",
    "variables": {
      "a": 2,
      "b": 1478,
      "c": 4,
      "d": 919
    }
  },
  {
    "answerOptions": [
      "4684",
      "4815",
      "4690",
      "5032"
    ],
    "correctAnswer": "4690",
    "variables": {
      "a": 1,
      "b": 890,
      "c": 4,
      "d": 950
    }
  },
  {
    "answerOptions": [
      "10806",
      "11284",
      "11138",
      "10466"
    ],
    "correctAnswer": "10466",
    "variables": {
      "a": 5,
      "b": 1496,
      "c": 2,
      "d": 1493
    }
  },
  {
    "answerOptions": [
      "1919",
      "1766",
      "1727",
      "1832"
    ],
    "correctAnswer": "1766",
    "variables": {
      "a": 1,
      "b": 903,
      "c": 1,
      "d": 863
    }
  },
  {
    "answerOptions": [
      "9423",
      "9503",
      "8547",
      "8543"
    ],
    "correctAnswer": "9423",
    "variables": {
      "a": 5,
      "b": 1297,
      "c": 2,
      "d": 1469
    }
  },
  {
    "answerOptions": [
      "5322",
      "5170",
      "5124",
      "5386"
    ],
    "correctAnswer": "5124",
    "variables": {
      "a": 3,
      "b": 1266,
      "c": 1,
      "d": 1326
    }
  },
  {
    "answerOptions": [
      "7120",
      "7043",
      "6887",
      "7540"
    ],
    "correctAnswer": "6887",
    "variables": {
      "a": 3,
      "b": 1327,
      "c": 2,
      "d": 1453
    }
  },
  {
    "answerOptions": [
      "11637",
      "12123",
      "12445",
      "12732"
    ],
    "correctAnswer": "12445",
    "variables": {
      "a": 5,
      "b": 1260,
      "c": 5,
      "d": 1229
    }
  },
  {
    "answerOptions": [
      "6563",
      "6582",
      "7135",
      "6807"
    ],
    "correctAnswer": "6582",
    "variables": {
      "a": 3,
      "b": 829,
      "c": 5,
      "d": 819
    }
  },
  {
    "answerOptions": [
      "5310",
      "4862",
      "5276",
      "4927"
    ],
    "correctAnswer": "5276",
    "variables": {
      "a": 4,
      "b": 1084,
      "c": 1,
      "d": 940
    }
  },
  {
    "answerOptions": [
      "7412",
      "7338",
      "6806",
      "7830"
    ],
    "correctAnswer": "7338",
    "variables": {
      "a": 2,
      "b": 1261,
      "c": 4,
      "d": 1204
    }
  },
  {
    "answerOptions": [
      "7388",
      "7671",
      "7532",
      "7834"
    ],
    "correctAnswer": "7671",
    "variables": {
      "a": 3,
      "b": 1301,
      "c": 4,
      "d": 942
    }
  },
  {
    "answerOptions": [
      "6209",
      "7225",
      "6582",
      "5951"
    ],
    "correctAnswer": "6582",
    "variables": {
      "a": 3,
      "b": 939,
      "c": 3,
      "d": 1255
    }
  },
  {
    "answerOptions": [
      "6192",
      "6542",
      "6824",
      "6660"
    ],
    "correctAnswer": "6824",
    "variables": {
      "a": 3,
      "b": 1172,
      "c": 4,
      "d": 827
    }
  },
  {
    "answerOptions": [
      "2435",
      "2418",
      "2521",
      "2211"
    ],
    "correctAnswer": "2418",
    "variables": {
      "a": 1,
      "b": 1448,
      "c": 1,
      "d": 970
    }
  },
  {
    "answerOptions": [
      "5276",
      "5615",
      "5479",
      "5891"
    ],
    "correctAnswer": "5479",
    "variables": {
      "a": 1,
      "b": 1435,
      "c": 3,
      "d": 1348
    }
  },
  {
    "answerOptions": [
      "9708",
      "9458",
      "8898",
      "8049"
    ],
    "correctAnswer": "8898",
    "variables": {
      "a": 5,
      "b": 1046,
      "c": 4,
      "d": 917
    }
  },
  {
    "answerOptions": [
      "4775",
      "5035",
      "5180",
      "4661"
    ],
    "correctAnswer": "4775",
    "variables": {
      "a": 3,
      "b": 1150,
      "c": 1,
      "d": 1325
    }
  },
  {
    "answerOptions": [
      "5850",
      "5329",
      "5429",
      "6113"
    ],
    "correctAnswer": "5850",
    "variables": {
      "a": 4,
      "b": 930,
      "c": 2,
      "d": 1065
    }
  },
  {
    "answerOptions": [
      "12376",
      "11372",
      "12488",
      "11332"
    ],
    "correctAnswer": "11372",
    "variables": {
      "a": 5,
      "b": 1496,
      "c": 4,
      "d": 973
    }
  },
  {
    "answerOptions": [
      "9516",
      "10413",
      "8610",
      "8764"
    ],
    "correctAnswer": "9516",
    "variables": {
      "a": 4,
      "b": 1361,
      "c": 4,
      "d": 1018
    }
  },
  {
    "answerOptions": [
      "9526",
      "8545",
      "8816",
      "8121"
    ],
    "correctAnswer": "8816",
    "variables": {
      "a": 3,
      "b": 1332,
      "c": 5,
      "d": 964
    }
  },
  {
    "answerOptions": [
      "5881",
      "5799",
      "5420",
      "4918"
    ],
    "correctAnswer": "5420",
    "variables": {
      "a": 2,
      "b": 1470,
      "c": 2,
      "d": 1240
    }
  },
  {
    "answerOptions": [
      "5439",
      "5506",
      "5635",
      "5171"
    ],
    "correctAnswer": "5439",
    "variables": {
      "a": 3,
      "b": 1412,
      "c": 1,
      "d": 1203
    }
  },
  {
    "answerOptions": [
      "5024",
      "5197",
      "5301",
      "5121"
    ],
    "correctAnswer": "5024",
    "variables": {
      "a": 2,
      "b": 1023,
      "c": 2,
      "d": 1489
    }
  },
  {
    "answerOptions": [
      "1962",
      "1902",
      "2081",
      "1958"
    ],
    "correctAnswer": "2081",
    "variables": {
      "a": 1,
      "b": 908,
      "c": 1,
      "d": 1173
    }
  },
  {
    "answerOptions": [
      "6384",
      "6438",
      "6891",
      "6399"
    ],
    "correctAnswer": "6399",
    "variables": {
      "a": 2,
      "b": 842,
      "c": 5,
      "d": 943
    }
  },
  {
    "answerOptions": [
      "9071",
      "9208",
      "10159",
      "9710"
    ],
    "correctAnswer": "9710",
    "variables": {
      "a": 3,
      "b": 1310,
      "c": 4,
      "d": 1445
    }
  }
]